{
  "geometry": "uniform-3-4-36-3262-63",
  "label": "3-uniform #4 (3^6; 3^2.6^2; 6^3)",
  "picker_group": "Periodic Mixed",
  "picker_order": 252,
  "family": "mixed",
  "viewport_sync_mode": "backend-sync",
  "sizing_policy": {
    "control": "cell_size",
    "default": 12,
    "min": 8,
    "max": 20
  },
  "default_rule": "life-b2-s23",
  "minimum_grid_dimension": 1,
  "source_urls": [
    "https://commons.wikimedia.org/wiki/File:3-uniform_4.svg"
  ],
  "palette": {
    "geometry": "uniform-3-4-36-3262-63",
    "variants": [
      {
        "label": "uniform-3-4-36-3262-63-hexagon",
        "selector": {
          "kind": "hexagon"
        },
        "color": {
          "token": "toneCream"
        }
      },
      {
        "label": "uniform-3-4-36-3262-63-triangle",
        "selector": {
          "kind": "triangle"
        },
        "color": {
          "token": "toneClay"
        }
      }
    ]
  },
  "preview_data": "toneCream:-13,42 -13,30 -2,24 8,30 8,42 -2,48;toneClay:-2,0 8,6 -2,12;toneClay:8,6 -2,0 8,-6;toneCream:18,-12 29,-6 29,6 18,12 8,6 8,-6;toneCream:18,24 8,30 -2,24 -2,12 8,6 18,12;toneCream:18,24 18,12 29,6 39,12 39,24 29,30;toneCream:18,48 18,60 8,66 -2,60 -2,48 8,42;toneCream:18,48 29,42 39,48 39,60 29,66 18,60;toneCream:29,42 29,30 39,24 50,30 50,42 39,48;toneClay:18,24 18,36 8,30;toneClay:18,36 8,42 8,30;toneClay:18,36 18,24 29,30;toneClay:18,36 18,48 8,42;toneClay:18,36 29,30 29,42;toneClay:18,36 29,42 18,48;toneClay:39,0 29,6 29,-6;toneClay:39,0 39,12 29,6;toneClay:39,0 50,6 39,12;toneClay:50,6 39,0 50,-6;toneClay:-2,72 -2,60 8,66;toneClay:8,78 -2,72 8,66;toneCream:18,60 29,66 29,78 18,84 8,78 8,66;toneClay:29,66 39,60 39,72;toneClay:39,72 29,78 29,66;toneClay:39,72 39,60 50,66;toneClay:50,78 39,72 50,66;toneCream:60,-12 70,-6 70,6 60,12 50,6 50,-6;toneCream:60,24 50,30 39,24 39,12 50,6 60,12;toneCream:60,24 60,12 70,6 81,12 81,24 70,30;toneCream:60,48 60,60 50,66 39,60 39,48 50,42;toneCream:60,48 70,42 81,48 81,60 70,66 60,60;toneCream:70,42 70,30 81,24 91,30 91,42 81,48;toneClay:60,24 60,36 50,30;toneClay:60,36 50,42 50,30;toneClay:60,36 60,24 70,30;toneClay:60,36 60,48 50,42;toneClay:60,36 70,30 70,42;toneClay:60,36 70,42 60,48;toneClay:81,0 70,6 70,-6;toneClay:81,0 81,12 70,6;toneClay:81,0 91,6 81,12;toneClay:91,6 81,0 91,-6;toneCream:102,-12 112,-6 112,6 102,12 91,6 91,-6;toneCream:102,24 91,30 81,24 81,12 91,6 102,12;toneCream:102,24 102,12 112,6 122,12 122,24 112,30;toneCream:102,48 102,60 91,66 81,60 81,48 91,42;toneCream:102,48 112,42 122,48 122,60 112,66 102,60;toneCream:112,42 112,30 122,24 133,30 133,42 122,48;toneClay:102,24 102,36 91,30;toneClay:102,36 91,42 91,30;toneClay:102,36 102,24 112,30;toneClay:102,36 102,48 91,42;toneClay:102,36 112,30 112,42;toneClay:102,36 112,42 102,48;toneClay:122,0 112,6 112,-6;toneClay:122,0 122,12 112,6;toneCream:60,60 70,66 70,78 60,84 50,78 50,66;toneClay:70,66 81,60 81,72;toneClay:81,72 70,78 70,66;toneClay:81,72 81,60 91,66;toneClay:91,78 81,72 91,66;toneCream:102,60 112,66 112,78 102,84 91,78 91,66;toneClay:112,66 122,60 122,72;toneClay:122,72 112,78 112,66"
}
